add_gitignore/__init__.py
add_gitignore/add_gitignore.py
add_gitignore/util/__init__.py
add_gitignore/util/file.py
add_gitignore/util/request.py
add_gitignore/util/response.py
add_gitignore-1.0.0.dist-info/DESCRIPTION.rst
add_gitignore-1.0.0.dist-info/METADATA
add_gitignore-1.0.0.dist-info/RECORD
add_gitignore-1.0.0.dist-info/WHEEL
add_gitignore-1.0.0.dist-info/entry_points.txt
add_gitignore-1.0.0.dist-info/metadata.json
add_gitignore-1.0.0.dist-info/top_level.txt
