Metadata-Version: 2.0
Name: add-gitignore
Version: 1.0.0
Summary: Generate Gitignore rules basing on GitHub's templates collection.
Home-page: https://github.com/FannyVieira/add-gitignore
Author: fanny vieira
Author-email: fannyvieira082@gmail.com
License: MIT License
Platform: UNKNOWN
Classifier: Programming Language :: Python :: 2.7
Classifier: License :: OSI Approved :: MIT License
Classifier: Operating System :: OS Independent
Requires-Dist: requests
